{"generated_at":"2026-04-20T22:09:50.791128+00:00","composite_score":53.0,"drawdown_risk_score":64.1,"sentiment_score":39.9,"liquidity_score":59.2,"valuation_score":77.2,"regime":"ELEVATED","risk_regime":"ELEVATED_RISK","score_velocity":-4.74,"score_acceleration":-25.82,"indicators":{"qqq_deviation":{"score":35.2,"raw_value":0.3523,"weight":0.17,"label":"QQQ Deviation"},"vix_level":{"score":38.4,"raw_value":0.3839,"weight":0.15,"label":"VIX Level"},"sector_breadth":{"score":41.3,"raw_value":0.4133,"weight":0.13,"label":"Sector Breadth"},"credit_spread":{"score":96.0,"raw_value":0.9598,"weight":0.13,"label":"Credit Spread"},"put_call_ratio":{"score":47.3,"raw_value":0.4727,"weight":0.14,"label":"Put/Call Ratio (SKEW)"},"yield_curve":{"score":40.3,"raw_value":0.4034,"weight":0.13,"label":"Yield Curve"},"cape_ratio":{"score":77.2,"raw_value":0.7724,"weight":0.15,"label":"CAPE Valuation"}},"confidence_interval":{"lower":51.0,"upper":55.3},"data_quality":{"indicators_available":7,"indicators_total":7,"completeness":100.0,"data_end_dates":{"qqq_deviation":"2026-04-20","vix_level":"2026-04-20","sector_breadth":"2026-04-20","credit_spread":"2026-04-20","put_call_ratio":"2026-04-20","yield_curve":"2026-04-20","cape_ratio":"2026-04-20"},"staleness_warning":false},"diagnostics":{"correlation_matrix":{"qqq_deviation":{"qqq_deviation":1.0,"vix_level":0.659,"sector_breadth":0.188,"credit_spread":-0.201,"put_call_ratio":0.069,"yield_curve":0.432,"cape_ratio":0.821},"vix_level":{"qqq_deviation":0.659,"vix_level":1.0,"sector_breadth":0.494,"credit_spread":0.321,"put_call_ratio":0.228,"yield_curve":0.561,"cape_ratio":0.689},"sector_breadth":{"qqq_deviation":0.188,"vix_level":0.494,"sector_breadth":1.0,"credit_spread":0.482,"put_call_ratio":-0.013,"yield_curve":0.409,"cape_ratio":0.041},"credit_spread":{"qqq_deviation":-0.201,"vix_level":0.321,"sector_breadth":0.482,"credit_spread":1.0,"put_call_ratio":0.007,"yield_curve":0.179,"cape_ratio":-0.173},"put_call_ratio":{"qqq_deviation":0.069,"vix_level":0.228,"sector_breadth":-0.013,"credit_spread":0.007,"put_call_ratio":1.0,"yield_curve":0.083,"cape_ratio":0.225},"yield_curve":{"qqq_deviation":0.432,"vix_level":0.561,"sector_breadth":0.409,"credit_spread":0.179,"put_call_ratio":0.083,"yield_curve":1.0,"cape_ratio":0.421},"cape_ratio":{"qqq_deviation":0.821,"vix_level":0.689,"sector_breadth":0.041,"credit_spread":-0.173,"put_call_ratio":0.225,"yield_curve":0.421,"cape_ratio":1.0}},"sensitivity":{"qqq_deviation":3.34,"vix_level":3.01,"sector_breadth":3.53,"credit_spread":2.65,"put_call_ratio":3.11,"yield_curve":4.04,"cape_ratio":3.5}},"previous_day":{"composite_score":56.9,"indicators":{"qqq_deviation":36.0,"vix_level":49.9,"sector_breadth":47.7,"credit_spread":96.0,"put_call_ratio":47.0,"yield_curve":45.3,"cape_ratio":81.0}}}