{"generated_at":"2026-03-26T21:53:47.422219+00:00","composite_score":29.5,"drawdown_risk_score":66.0,"sentiment_score":22.7,"liquidity_score":35.5,"valuation_score":35.1,"regime":"LOW","risk_regime":"ELEVATED_RISK","score_velocity":2.1,"score_acceleration":2.45,"indicators":{"qqq_deviation":{"score":5.9,"raw_value":0.0589,"weight":0.17,"label":"QQQ Deviation"},"vix_level":{"score":8.3,"raw_value":0.0827,"weight":0.15,"label":"VIX Level"},"sector_breadth":{"score":6.8,"raw_value":0.0681,"weight":0.13,"label":"Sector Breadth"},"credit_spread":{"score":84.0,"raw_value":0.8405,"weight":0.13,"label":"Credit Spread"},"put_call_ratio":{"score":58.6,"raw_value":0.5856,"weight":0.14,"label":"Put/Call Ratio (SKEW)"},"yield_curve":{"score":15.5,"raw_value":0.155,"weight":0.13,"label":"Yield Curve"},"cape_ratio":{"score":35.1,"raw_value":0.3509,"weight":0.15,"label":"CAPE Valuation"}},"confidence_interval":{"lower":27.2,"upper":31.6},"data_quality":{"indicators_available":7,"indicators_total":7,"completeness":100.0,"data_end_dates":{"qqq_deviation":"2026-03-26","vix_level":"2026-03-26","sector_breadth":"2026-03-26","credit_spread":"2026-03-26","put_call_ratio":"2026-03-26","yield_curve":"2026-03-26","cape_ratio":"2026-03-26"},"staleness_warning":false},"diagnostics":{"correlation_matrix":{"qqq_deviation":{"qqq_deviation":1.0,"vix_level":0.694,"sector_breadth":0.171,"credit_spread":-0.056,"put_call_ratio":0.283,"yield_curve":0.166,"cape_ratio":0.837},"vix_level":{"qqq_deviation":0.694,"vix_level":1.0,"sector_breadth":0.447,"credit_spread":0.422,"put_call_ratio":0.424,"yield_curve":0.376,"cape_ratio":0.736},"sector_breadth":{"qqq_deviation":0.171,"vix_level":0.447,"sector_breadth":1.0,"credit_spread":0.516,"put_call_ratio":0.026,"yield_curve":0.408,"cape_ratio":0.028},"credit_spread":{"qqq_deviation":-0.056,"vix_level":0.422,"sector_breadth":0.516,"credit_spread":1.0,"put_call_ratio":0.054,"yield_curve":0.363,"cape_ratio":-0.027},"put_call_ratio":{"qqq_deviation":0.283,"vix_level":0.424,"sector_breadth":0.026,"credit_spread":0.054,"put_call_ratio":1.0,"yield_curve":0.046,"cape_ratio":0.477},"yield_curve":{"qqq_deviation":0.166,"vix_level":0.376,"sector_breadth":0.408,"credit_spread":0.363,"put_call_ratio":0.046,"yield_curve":1.0,"cape_ratio":0.129},"cape_ratio":{"qqq_deviation":0.837,"vix_level":0.736,"sector_breadth":0.028,"credit_spread":-0.027,"put_call_ratio":0.477,"yield_curve":0.129,"cape_ratio":1.0}},"sensitivity":{"qqq_deviation":3.07,"vix_level":2.67,"sector_breadth":3.23,"credit_spread":2.93,"put_call_ratio":2.83,"yield_curve":3.74,"cape_ratio":3.22}},"previous_day":{"composite_score":29.3,"indicators":{"qqq_deviation":7.8,"vix_level":12.1,"sector_breadth":6.8,"credit_spread":78.4,"put_call_ratio":44.2,"yield_curve":20.8,"cape_ratio":41.4}}}