{
  "model_version": "4.1",
  "calibration_date": "2026-06-09",
  "data_points": 6649,
  "train_test_split": "purged_wfcv_5fold",
  "actual_folds_used": {
    "drawdown_10pct": 5,
    "drawdown_20pct": 3
  },
  "purge_days": 120,
  "embargo_days": 20,
  "effective_sample_size": 166,
  "forward_window_days": 180,
  "forward_window_label": "9 months",
  "firth_enabled": false,
  "feature_names": [
    "ind_credit_spread",
    "ind_qqq_deviation",
    "ind_vix_level",
    "ind_vix_level_change_5d",
    "ind_yield_curve",
    "risk_ema_20d",
    "score_std_20d",
    "score_velocity",
    "vix_x_credit"
  ],
  "current_features": {
    "composite_score": 53.0,
    "drawdown_risk_score": 62.6,
    "ind_credit_spread": 98.3,
    "ind_qqq_deviation": 72.3,
    "ind_vix_level": 27.1,
    "ind_vix_level_change_5d": -47.5,
    "ind_yield_curve": 10.3,
    "risk_ema_20d": 59.8771,
    "score_std_20d": 4.8788,
    "score_velocity": -14.4,
    "vix_x_credit": 26.6393
  },
  "logistic_coefficients": {
    "drawdown_10pct": {
      "features": [
        "risk_ema_20d",
        "ind_qqq_deviation",
        "ind_credit_spread",
        "ind_yield_curve",
        "ind_vix_level",
        "vix_x_credit",
        "ind_vix_level_change_5d",
        "score_velocity"
      ],
      "dd_definition": "peak_to_trough",
      "forward_window": 180,
      "regularization_C": 5.0,
      "penalty": "l1",
      "n_total": 6640,
      "n_events": 4702,
      "base_rate": 0.7081,
      "weights": {
        "risk_ema_20d": -0.119188,
        "ind_qqq_deviation": -0.117542,
        "ind_credit_spread": 0.033439,
        "ind_yield_curve": 0.056811,
        "ind_vix_level": -0.212438,
        "vix_x_credit": -0.132774,
        "ind_vix_level_change_5d": 0.050225,
        "score_velocity": 0.010262
      },
      "intercept": 0.917652,
      "scaler_mean": {
        "risk_ema_20d": 52.956029,
        "ind_qqq_deviation": 51.422605,
        "ind_credit_spread": 70.009443,
        "ind_yield_curve": 47.838313,
        "ind_vix_level": 56.149383,
        "vix_x_credit": 40.297283,
        "ind_vix_level_change_5d": 0.020226,
        "score_velocity": 0.085458
      },
      "scaler_std": {
        "risk_ema_20d": 8.598256,
        "ind_qqq_deviation": 27.714532,
        "ind_credit_spread": 24.88448,
        "ind_yield_curve": 31.70942,
        "ind_vix_level": 29.405758,
        "vix_x_credit": 23.692039,
        "ind_vix_level_change_5d": 17.402141,
        "score_velocity": 9.188138
      },
      "auc_train": 0.6093,
      "auc_test": 0.4612,
      "brier_train": 0.2007,
      "bss_test": -0.8208,
      "cv_metrics": {
        "method": "purged_walk_forward_5fold",
        "purge_days": 120,
        "embargo_days": 20,
        "auc_mean": 0.4612,
        "auc_std": 0.1845,
        "bss_mean": -0.8208,
        "bss_std": 0.6923,
        "ece_mean": 0.2968,
        "ece_std": 0.1514,
        "per_fold": [
          {
            "fold": 1,
            "train_range": "1999-12-31 → 2009-03-30",
            "test_range": "2009-09-21 → 2012-08-29",
            "n_train": 2324,
            "n_test": 743,
            "base_rate_train": 0.7917,
            "base_rate_test": 0.8237,
            "auc": 0.7677,
            "brier": 0.1366,
            "bss": 0.0597,
            "ece": 0.0878
          },
          {
            "fold": 2,
            "train_range": "1999-12-31 → 2012-03-09",
            "test_range": "2012-08-30 → 2015-08-14",
            "n_train": 3067,
            "n_test": 743,
            "base_rate_train": 0.7675,
            "base_rate_test": 0.2719,
            "auc": 0.3061,
            "brier": 0.5763,
            "bss": -1.911,
            "ece": 0.5459
          },
          {
            "fold": 3,
            "train_range": "1999-12-31 → 2015-02-24",
            "test_range": "2015-08-17 → 2018-07-27",
            "n_train": 3810,
            "n_test": 743,
            "base_rate_train": 0.6709,
            "base_rate_test": 0.5343,
            "auc": 0.3,
            "brier": 0.3961,
            "bss": -0.5918,
            "ece": 0.3361
          },
          {
            "fold": 4,
            "train_range": "1999-12-31 → 2018-02-05",
            "test_range": "2018-07-30 → 2021-07-12",
            "n_train": 4553,
            "n_test": 743,
            "base_rate_train": 0.6486,
            "base_rate_test": 0.8964,
            "auc": 0.3518,
            "brier": 0.2105,
            "bss": -1.2663,
            "ece": 0.3028
          },
          {
            "fold": 5,
            "train_range": "1999-12-31 → 2021-01-19",
            "test_range": "2021-07-13 → 2024-06-25",
            "n_train": 5296,
            "n_test": 743,
            "base_rate_train": 0.6934,
            "base_rate_test": 0.8439,
            "auc": 0.5804,
            "brier": 0.1838,
            "bss": -0.3947,
            "ece": 0.2116
          }
        ]
      }
    },
    "drawdown_20pct": {
      "features": [
        "risk_ema_20d",
        "score_std_20d"
      ],
      "dd_definition": "peak_to_trough",
      "forward_window": 180,
      "regularization_C": 1.0,
      "penalty": "l2",
      "n_total": 6640,
      "n_events": 1781,
      "base_rate": 0.2682,
      "weights": {
        "risk_ema_20d": -0.299896,
        "score_std_20d": 0.128515
      },
      "intercept": -1.024901,
      "scaler_mean": {
        "risk_ema_20d": 52.956029,
        "score_std_20d": 6.588234
      },
      "scaler_std": {
        "risk_ema_20d": 8.598256,
        "score_std_20d": 2.803007
      },
      "auc_train": 0.5961,
      "auc_test": 0.3207,
      "brier_train": 0.1914,
      "bss_test": -0.274,
      "cv_metrics": {
        "method": "purged_walk_forward_3fold",
        "purge_days": 120,
        "embargo_days": 20,
        "auc_mean": 0.3207,
        "auc_std": 0.1646,
        "bss_mean": -0.274,
        "bss_std": 0.0541,
        "ece_mean": 0.216,
        "ece_std": 0.0568,
        "per_fold": [
          {
            "fold": 3,
            "train_range": "1999-12-31 → 2015-02-24",
            "test_range": "2015-08-17 → 2018-07-27",
            "n_train": 3810,
            "n_test": 743,
            "base_rate_train": 0.2722,
            "base_rate_test": 0.1063,
            "auc": 0.1152,
            "brier": 0.1213,
            "bss": -0.2761,
            "ece": 0.1459
          },
          {
            "fold": 4,
            "train_range": "1999-12-31 → 2018-02-05",
            "test_range": "2018-07-30 → 2021-07-12",
            "n_train": 4553,
            "n_test": 743,
            "base_rate_train": 0.2278,
            "base_rate_test": 0.3163,
            "auc": 0.5182,
            "brier": 0.261,
            "bss": -0.2067,
            "ece": 0.2172
          },
          {
            "fold": 5,
            "train_range": "1999-12-31 → 2021-01-19",
            "test_range": "2021-07-13 → 2024-06-25",
            "n_train": 5296,
            "n_test": 743,
            "base_rate_train": 0.253,
            "base_rate_test": 0.3755,
            "auc": 0.3288,
            "brier": 0.314,
            "bss": -0.3392,
            "ece": 0.285
          }
        ]
      }
    }
  },
  "bayesian_lookup": {
    "drawdown_10pct": {
      "bin_centers": [
        10,
        30,
        50,
        70,
        90
      ],
      "probabilities": [
        0.0606,
        0.4595,
        0.8515,
        0.8515,
        0.8515
      ]
    },
    "drawdown_20pct": {
      "bin_centers": [
        10,
        30,
        50,
        70,
        90
      ],
      "probabilities": [
        0.0161,
        0.2857,
        0.3617,
        0.4855,
        0.4855
      ]
    },
    "drawdown_30pct": {
      "bin_centers": [
        10,
        30,
        50,
        70,
        90
      ],
      "probabilities": [
        0.0041,
        0.1314,
        0.1314,
        0.1314,
        0.2353
      ]
    }
  },
  "evt_parameters": {
    "gpd_shape_xi": 0.2547,
    "gpd_scale_sigma": 0.0879,
    "threshold_u": 0.1,
    "n_exceedances": 4702,
    "exceedance_ratios": {
      "20pct_given_10pct": 0.3788,
      "30pct_given_10pct": 0.1846,
      "40pct_given_10pct": 0.1297
    },
    "empirical_cross_ratios": {
      "20pct_given_10pct": 0.3788,
      "30pct_given_10pct": 0.1846,
      "40pct_given_10pct": 0.1297
    },
    "cross_ratios": {
      "40pct_given_30pct": 0.7026,
      "40pct_given_20pct": 0.3424
    }
  },
  "empirical_stats": {
    "0-20": {
      "count": 163,
      "p_10pct": 0.8773,
      "n_10pct": 143,
      "p_20pct": 0.3374,
      "n_20pct": 55,
      "p_30pct": 0.0675,
      "n_30pct": 11,
      "p_40pct": 0.0245,
      "n_40pct": 4,
      "mean_dd": 17.1,
      "median_dd": 12.84,
      "p95_dd": 34.25
    },
    "20-40": {
      "count": 1271,
      "p_10pct": 0.7844,
      "n_10pct": 997,
      "p_20pct": 0.4099,
      "n_20pct": 521,
      "p_30pct": 0.2258,
      "n_30pct": 287,
      "p_40pct": 0.1629,
      "n_40pct": 207,
      "mean_dd": 21.54,
      "median_dd": 16.11,
      "p95_dd": 47.93
    },
    "40-60": {
      "count": 2293,
      "p_10pct": 0.713,
      "n_10pct": 1635,
      "p_20pct": 0.3022,
      "n_20pct": 693,
      "p_30pct": 0.1888,
      "n_30pct": 433,
      "p_40pct": 0.1348,
      "n_40pct": 309,
      "mean_dd": 19.3,
      "median_dd": 13.47,
      "p95_dd": 54.22
    },
    "60-80": {
      "count": 2616,
      "p_10pct": 0.6747,
      "n_10pct": 1765,
      "p_20pct": 0.1858,
      "n_20pct": 486,
      "p_30pct": 0.0516,
      "n_30pct": 135,
      "p_40pct": 0.0344,
      "n_40pct": 90,
      "mean_dd": 14.21,
      "median_dd": 11.72,
      "p95_dd": 32.35
    },
    "80-100": {
      "count": 297,
      "p_10pct": 0.5455,
      "n_10pct": 162,
      "p_20pct": 0.0875,
      "n_20pct": 26,
      "p_30pct": 0.0067,
      "n_30pct": 2,
      "p_40pct": 0.0,
      "n_40pct": 0,
      "mean_dd": 11.88,
      "median_dd": 10.78,
      "p95_dd": 28.56
    }
  },
  "unconditional_base_rates": {
    "10pct": 0.7081,
    "20pct": 0.2682,
    "30pct": 0.1307,
    "40pct": 0.0919
  },
  "probability_ci": {
    "10pct": {
      "lower": 0.8455,
      "upper": 0.8554,
      "ci_level": 0.9
    },
    "20pct": {
      "lower": 0.3477,
      "upper": 0.4998,
      "ci_level": 0.9
    },
    "30pct": {
      "lower": 0.0976,
      "upper": 0.1716,
      "ci_level": 0.9
    }
  },
  "blend_weights": {
    "10pct": {
      "logistic": 0.0,
      "bayesian": 1.0
    },
    "20pct": {
      "logistic": 0.0,
      "bayesian": 1.0
    },
    "30pct": {
      "logistic": 0.0,
      "bayesian": 1.0
    }
  },
  "confidence_tiers": {
    "10pct": "moderate",
    "20pct": "moderate",
    "30pct": "model_dependent",
    "40pct": "extrapolated"
  }
}
