{
  "model_version": "4.1",
  "calibration_date": "2026-06-01",
  "data_points": 6643,
  "train_test_split": "purged_wfcv_5fold",
  "actual_folds_used": {
    "drawdown_10pct": 5,
    "drawdown_20pct": 3
  },
  "purge_days": 120,
  "embargo_days": 20,
  "effective_sample_size": 166,
  "forward_window_days": 180,
  "forward_window_label": "9 months",
  "firth_enabled": false,
  "feature_names": [
    "ind_credit_spread",
    "ind_qqq_deviation",
    "ind_vix_level",
    "ind_vix_level_change_5d",
    "ind_yield_curve",
    "risk_ema_20d",
    "score_std_20d",
    "score_velocity",
    "vix_x_credit"
  ],
  "current_features": {
    "composite_score": 67.8,
    "drawdown_risk_score": 55.3,
    "ind_credit_spread": 97.1,
    "ind_qqq_deviation": 97.8,
    "ind_vix_level": 71.8,
    "ind_vix_level_change_5d": 11.4,
    "ind_yield_curve": 10.1,
    "risk_ema_20d": 59.2496,
    "score_std_20d": 3.1953,
    "score_velocity": -0.73,
    "vix_x_credit": 69.7178
  },
  "logistic_coefficients": {
    "drawdown_10pct": {
      "features": [
        "risk_ema_20d",
        "ind_qqq_deviation",
        "ind_credit_spread",
        "ind_yield_curve",
        "ind_vix_level",
        "vix_x_credit",
        "ind_vix_level_change_5d",
        "score_velocity"
      ],
      "dd_definition": "peak_to_trough",
      "forward_window": 180,
      "regularization_C": 5.0,
      "penalty": "l1",
      "n_total": 6634,
      "n_events": 4702,
      "base_rate": 0.7088,
      "weights": {
        "risk_ema_20d": -0.117026,
        "ind_qqq_deviation": -0.110132,
        "ind_credit_spread": 0.038365,
        "ind_yield_curve": 0.054,
        "ind_vix_level": -0.218638,
        "vix_x_credit": -0.133956,
        "ind_vix_level_change_5d": 0.055819,
        "score_velocity": 0.006663
      },
      "intercept": 0.920499,
      "scaler_mean": {
        "risk_ema_20d": 52.94881,
        "ind_qqq_deviation": 51.381233,
        "ind_credit_spread": 69.983765,
        "ind_yield_curve": 47.860597,
        "ind_vix_level": 56.15009,
        "vix_x_credit": 40.284441,
        "ind_vix_level_change_5d": 0.009542,
        "score_velocity": 0.084332
      },
      "scaler_std": {
        "risk_ema_20d": 8.598829,
        "ind_qqq_deviation": 27.698376,
        "ind_credit_spread": 24.880857,
        "ind_yield_curve": 31.713066,
        "ind_vix_level": 29.417787,
        "vix_x_credit": 23.697633,
        "ind_vix_level_change_5d": 17.403587,
        "score_velocity": 9.192172
      },
      "auc_train": 0.6086,
      "auc_test": 0.4634,
      "brier_train": 0.2005,
      "bss_test": -0.812,
      "cv_metrics": {
        "method": "purged_walk_forward_5fold",
        "purge_days": 120,
        "embargo_days": 20,
        "auc_mean": 0.4634,
        "auc_std": 0.1876,
        "bss_mean": -0.812,
        "bss_std": 0.7023,
        "ece_mean": 0.2929,
        "ece_std": 0.1543,
        "per_fold": [
          {
            "fold": 1,
            "train_range": "1999-12-31 → 2009-03-25",
            "test_range": "2009-09-16 → 2012-08-23",
            "n_train": 2321,
            "n_test": 742,
            "base_rate_train": 0.7928,
            "base_rate_test": 0.8235,
            "auc": 0.777,
            "brier": 0.1341,
            "bss": 0.0774,
            "ece": 0.0774
          },
          {
            "fold": 2,
            "train_range": "1999-12-31 → 2012-03-05",
            "test_range": "2012-08-24 → 2015-08-07",
            "n_train": 3063,
            "n_test": 742,
            "base_rate_train": 0.7672,
            "base_rate_test": 0.2709,
            "auc": 0.3105,
            "brier": 0.5765,
            "bss": -1.9187,
            "ece": 0.5473
          },
          {
            "fold": 3,
            "train_range": "1999-12-31 → 2015-02-17",
            "test_range": "2015-08-10 → 2018-07-19",
            "n_train": 3805,
            "n_test": 742,
            "base_rate_train": 0.6704,
            "base_rate_test": 0.5337,
            "auc": 0.3139,
            "brier": 0.388,
            "bss": -0.5592,
            "ece": 0.326
          },
          {
            "fold": 4,
            "train_range": "1999-12-31 → 2018-01-26",
            "test_range": "2018-07-20 → 2021-06-30",
            "n_train": 4547,
            "n_test": 742,
            "base_rate_train": 0.6481,
            "base_rate_test": 0.8962,
            "auc": 0.3317,
            "brier": 0.211,
            "bss": -1.269,
            "ece": 0.303
          },
          {
            "fold": 5,
            "train_range": "1999-12-31 → 2021-01-07",
            "test_range": "2021-07-01 → 2024-06-12",
            "n_train": 5289,
            "n_test": 742,
            "base_rate_train": 0.6929,
            "base_rate_test": 0.8437,
            "auc": 0.5837,
            "brier": 0.1834,
            "bss": -0.3907,
            "ece": 0.2108
          }
        ]
      }
    },
    "drawdown_20pct": {
      "features": [
        "risk_ema_20d",
        "score_std_20d"
      ],
      "dd_definition": "peak_to_trough",
      "forward_window": 180,
      "regularization_C": 1.0,
      "penalty": "l2",
      "n_total": 6634,
      "n_events": 1781,
      "base_rate": 0.2685,
      "weights": {
        "risk_ema_20d": -0.29876,
        "score_std_20d": 0.12762
      },
      "intercept": -1.023458,
      "scaler_mean": {
        "risk_ema_20d": 52.94881,
        "score_std_20d": 6.590132
      },
      "scaler_std": {
        "risk_ema_20d": 8.598829,
        "score_std_20d": 2.803519
      },
      "auc_train": 0.5958,
      "auc_test": 0.3191,
      "brier_train": 0.1915,
      "bss_test": -0.2873,
      "cv_metrics": {
        "method": "purged_walk_forward_3fold",
        "purge_days": 120,
        "embargo_days": 20,
        "auc_mean": 0.3191,
        "auc_std": 0.1646,
        "bss_mean": -0.2873,
        "bss_std": 0.0627,
        "ece_mean": 0.2177,
        "ece_std": 0.0626,
        "per_fold": [
          {
            "fold": 3,
            "train_range": "1999-12-31 → 2015-02-17",
            "test_range": "2015-08-10 → 2018-07-19",
            "n_train": 3805,
            "n_test": 742,
            "base_rate_train": 0.2725,
            "base_rate_test": 0.0984,
            "auc": 0.1143,
            "brier": 0.1152,
            "bss": -0.2986,
            "ece": 0.1414
          },
          {
            "fold": 4,
            "train_range": "1999-12-31 → 2018-01-26",
            "test_range": "2018-07-20 → 2021-06-30",
            "n_train": 4547,
            "n_test": 742,
            "base_rate_train": 0.2281,
            "base_rate_test": 0.3154,
            "auc": 0.5173,
            "brier": 0.2603,
            "bss": -0.2054,
            "ece": 0.2169
          },
          {
            "fold": 5,
            "train_range": "1999-12-31 → 2021-01-07",
            "test_range": "2021-07-01 → 2024-06-12",
            "n_train": 5289,
            "n_test": 742,
            "base_rate_train": 0.2534,
            "base_rate_test": 0.3854,
            "auc": 0.3257,
            "brier": 0.3216,
            "bss": -0.3578,
            "ece": 0.2947
          }
        ]
      }
    }
  },
  "bayesian_lookup": {
    "drawdown_10pct": {
      "bin_centers": [
        10,
        30,
        50,
        70,
        90
      ],
      "probabilities": [
        0.0606,
        0.4595,
        0.8515,
        0.8515,
        0.8515
      ]
    },
    "drawdown_20pct": {
      "bin_centers": [
        10,
        30,
        50,
        70,
        90
      ],
      "probabilities": [
        0.0161,
        0.2857,
        0.3617,
        0.4855,
        0.4855
      ]
    },
    "drawdown_30pct": {
      "bin_centers": [
        10,
        30,
        50,
        70,
        90
      ],
      "probabilities": [
        0.0041,
        0.1314,
        0.1314,
        0.1314,
        0.2353
      ]
    }
  },
  "evt_parameters": {
    "gpd_shape_xi": 0.2547,
    "gpd_scale_sigma": 0.0879,
    "threshold_u": 0.1,
    "n_exceedances": 4702,
    "exceedance_ratios": {
      "20pct_given_10pct": 0.3788,
      "30pct_given_10pct": 0.1846,
      "40pct_given_10pct": 0.1297
    },
    "empirical_cross_ratios": {
      "20pct_given_10pct": 0.3788,
      "30pct_given_10pct": 0.1846,
      "40pct_given_10pct": 0.1297
    },
    "cross_ratios": {
      "40pct_given_30pct": 0.7026,
      "40pct_given_20pct": 0.3424
    }
  },
  "empirical_stats": {
    "0-20": {
      "count": 163,
      "p_10pct": 0.8773,
      "n_10pct": 143,
      "p_20pct": 0.3374,
      "n_20pct": 55,
      "p_30pct": 0.0675,
      "n_30pct": 11,
      "p_40pct": 0.0245,
      "n_40pct": 4,
      "mean_dd": 17.1,
      "median_dd": 12.84,
      "p95_dd": 34.25
    },
    "20-40": {
      "count": 1271,
      "p_10pct": 0.7844,
      "n_10pct": 997,
      "p_20pct": 0.4099,
      "n_20pct": 521,
      "p_30pct": 0.2258,
      "n_30pct": 287,
      "p_40pct": 0.1629,
      "n_40pct": 207,
      "mean_dd": 21.52,
      "median_dd": 16.11,
      "p95_dd": 47.93
    },
    "40-60": {
      "count": 2293,
      "p_10pct": 0.713,
      "n_10pct": 1635,
      "p_20pct": 0.3022,
      "n_20pct": 693,
      "p_30pct": 0.1888,
      "n_30pct": 433,
      "p_40pct": 0.1348,
      "n_40pct": 309,
      "mean_dd": 19.28,
      "median_dd": 13.47,
      "p95_dd": 54.22
    },
    "60-80": {
      "count": 2610,
      "p_10pct": 0.6762,
      "n_10pct": 1765,
      "p_20pct": 0.1862,
      "n_20pct": 486,
      "p_30pct": 0.0517,
      "n_30pct": 135,
      "p_40pct": 0.0345,
      "n_40pct": 90,
      "mean_dd": 14.21,
      "median_dd": 11.72,
      "p95_dd": 32.35
    },
    "80-100": {
      "count": 297,
      "p_10pct": 0.5455,
      "n_10pct": 162,
      "p_20pct": 0.0875,
      "n_20pct": 26,
      "p_30pct": 0.0067,
      "n_30pct": 2,
      "p_40pct": 0.0,
      "n_40pct": 0,
      "mean_dd": 11.88,
      "median_dd": 10.78,
      "p95_dd": 28.56
    }
  },
  "unconditional_base_rates": {
    "10pct": 0.7088,
    "20pct": 0.2685,
    "30pct": 0.1308,
    "40pct": 0.092
  },
  "probability_ci": {
    "10pct": {
      "lower": 0.846,
      "upper": 0.8556,
      "ci_level": 0.9
    },
    "20pct": {
      "lower": 0.3214,
      "upper": 0.4612,
      "ci_level": 0.9
    },
    "30pct": {
      "lower": 0.1004,
      "upper": 0.1729,
      "ci_level": 0.9
    }
  },
  "blend_weights": {
    "10pct": {
      "logistic": 0.0,
      "bayesian": 1.0
    },
    "20pct": {
      "logistic": 0.0,
      "bayesian": 1.0
    },
    "30pct": {
      "logistic": 0.0,
      "bayesian": 1.0
    }
  },
  "confidence_tiers": {
    "10pct": "moderate",
    "20pct": "moderate",
    "30pct": "model_dependent",
    "40pct": "extrapolated"
  }
}
